Metadata-Version: 2.1
Name: pandoc-run-filter
Version: 0.2.0
Summary: A simple filter for pandoc that runs shell commands and scripts and outputs as text and images.
Home-page: https://github.com/johnlwhiteman/pandoc-run-filter
Author: John L. Whiteman
Author-email: me@johnlwhiteman.com
License: BSD-3-Clause
Download-URL: https://github.com/johnlwhiteman/pandoc-run-filter/archive/v0.2.0.tar.gz
Keywords: pandoc,filter
Platform: UNKNOWN
Classifier: Development Status :: 3 - Alpha
Classifier: Environment :: Console
Classifier: Programming Language :: Python :: 3
Classifier: Programming Language :: Python :: 3.4
Classifier: Programming Language :: Python :: 3.6
Classifier: Programming Language :: Python :: 3.7
Classifier: License :: OSI Approved :: BSD License
Classifier: Operating System :: OS Independent
Classifier: Intended Audience :: End Users/Desktop
Classifier: Intended Audience :: Developers
Classifier: Topic :: Text Processing :: Filters
Classifier: Natural Language :: English
Requires-Python: >=3.6
Provides-Extra: dev
